[
    {
        "key": "dbln",
        "value": "%7B%22100008628047634%22%3A%22L35bA4ax%22%2C%22100049415292931%22%3A%22EqqbIwDa%22%7D",
        "domain": "facebook.com",
        "path": "/login/device-based/",
        "hostOnly": false,
        "creation": "2020-10-15T02:47:45.306Z",
        "lastAccessed": "2020-10-15T02:47:45.306Z"
    },
    {
        "key": "datr",
        "value": "e5eFXz3d1Et2QfODaoKXS8W2",
        "domain": "facebook.com",
        "path": "/",
        "hostOnly": false,
        "creation": "2020-10-15T02:47:45.306Z",
        "lastAccessed": "2020-10-15T02:47:45.306Z"
    },
    {
        "key": "sb",
        "value": "e5eFXzrGgbf-vhh8ZQ6kPKW8",
        "domain": "facebook.com",
        "path": "/",
        "hostOnly": false,
        "creation": "2020-10-15T02:47:45.306Z",
        "lastAccessed": "2020-10-15T02:47:45.306Z"
    },
    {
        "key": "dpr",
        "value": "2",
        "domain": "facebook.com",
        "path": "/",
        "hostOnly": false,
        "creation": "2020-10-15T02:47:45.306Z",
        "lastAccessed": "2020-10-15T02:47:45.306Z"
    },
    {
        "key": "locale",
        "value": "vi_VN",
        "domain": "facebook.com",
        "path": "/",
        "hostOnly": false,
        "creation": "2020-10-15T02:47:45.306Z",
        "lastAccessed": "2020-10-15T02:47:45.306Z"
    },
    {
        "key": "c_user",
        "value": "100049415292931",
        "domain": "facebook.com",
        "path": "/",
        "hostOnly": false,
        "creation": "2020-10-15T02:47:45.306Z",
        "lastAccessed": "2020-10-15T02:47:45.306Z"
    },
    {
        "key": "xs",
        "value": "2%3AoVcTfVbICRdPeg%3A2%3A1602728269%3A16226%3A6301",
        "domain": "facebook.com",
        "path": "/",
        "hostOnly": false,
        "creation": "2020-10-15T02:47:45.306Z",
        "lastAccessed": "2020-10-15T02:47:45.306Z"
    },
    {
        "key": "spin",
        "value": "r.1002824697_b.trunk_t.1602729104_s.1_v.2_",
        "domain": "facebook.com",
        "path": "/",
        "hostOnly": false,
        "creation": "2020-10-15T02:47:45.306Z",
        "lastAccessed": "2020-10-15T02:47:45.306Z"
    },
    {
        "key": "presence",
        "value": "EDvF3EtimeF1602729886EuserFA21B49415292931A2EstateFDutF1602729886528CEchF_7bCC",
        "domain": "facebook.com",
        "path": "/",
        "hostOnly": false,
        "creation": "2020-10-15T02:47:45.306Z",
        "lastAccessed": "2020-10-15T02:47:45.306Z"
    },
    {
        "key": "fr",
        "value": "1NKgiCShgSmke1KqB.AWVeZNdcfFGlpEZnaUa4FQC9Cz4.Bfh5UV.c8.F-H.0.0.Bfh7fO.AWWVplqrwcs",
        "domain": "facebook.com",
        "path": "/",
        "hostOnly": false,
        "creation": "2020-10-15T02:47:45.306Z",
        "lastAccessed": "2020-10-15T02:47:45.306Z"
    },
    {
        "key": "wd",
        "value": "982x439",
        "domain": "facebook.com",
        "path": "/",
        "hostOnly": false,
        "creation": "2020-10-15T02:47:45.306Z",
        "lastAccessed": "2020-10-15T02:47:45.306Z"
    }
]